<?xml version="1.0"?>
<post><user>jacob</user><title>Codex Updates</title><datetime>1322739424</datetime><body>All pages on the <link page="codex/">Codex</link> are now working, or at least can be reached, and many errors have been fixed within the codex. More information is currently being retrieved for use in the Codex, and styling will need to take place, but all pages are now rendering, at least.</body><tags><tag>codex</tag><tag>website update</tag><tag>update</tag></tags><comments/></post>
